dict_from_pypinyin/__init__.py
dict_from_pypinyin/api.py
dict_from_pypinyin/argparse_helper.py
dict_from_pypinyin/cli.py
dict_from_pypinyin/core.py
dict_from_pypinyin/logging_configuration.py
dict_from_pypinyin/main.py
dict_from_pypinyin/transcription.py
dict_from_pypinyin_tests/__init__.py
dict_from_pypinyin_tests/core_py/test_convert_chinese_to_pinyin.py
dict_from_pypinyin_tests/transcription_py/__init__.py
dict_from_pypinyin_tests/transcription_py/test_word_to_pinyin.py
dict_from_pypinyin-0.0.2.dist-info/LICENSE
dict_from_pypinyin-0.0.2.dist-info/METADATA
dict_from_pypinyin-0.0.2.dist-info/WHEEL
dict_from_pypinyin-0.0.2.dist-info/entry_points.txt
dict_from_pypinyin-0.0.2.dist-info/top_level.txt
dict_from_pypinyin-0.0.2.dist-info/RECORD
